screenshot_ocr/__init__.py
screenshot_ocr/app.py
screenshot_ocr/app_paths.py
screenshot_ocr/cli.py
screenshot_ocr/google_sheets.py
screenshot_ocr/ocr.py
screenshot_ocr/trivia.py
screenshot_ocr/utils.py
screenshot_ocr-0.3.0.dist-info/LICENSE
screenshot_ocr-0.3.0.dist-info/METADATA
screenshot_ocr-0.3.0.dist-info/WHEEL
screenshot_ocr-0.3.0.dist-info/entry_points.txt
screenshot_ocr-0.3.0.dist-info/top_level.txt
screenshot_ocr-0.3.0.dist-info/RECORD
