Metadata-Version: 2.1
Name: screenshot-ocr
Version: 0.3.0
Summary: Extract text from screenshots.
Project-URL: Homepage, https://github.com/cofiem/screenshot-ocr
Project-URL: Changelog, https://github.com/cofiem/screenshot-ocr/blob/main/CHANGELOG.md
Project-URL: Source, https://github.com/cofiem/screenshot-ocr
Project-URL: Tracker, https://github.com/cofiem/screenshot-ocr/issues
Classifier: Development Status :: 3 - Alpha
Classifier: License :: OSI Approved :: Apache Software License
Classifier: Operating System :: POSIX :: Linux
Classifier: Operating System :: Microsoft :: Windows
Classifier: Environment :: Console
Classifier: Programming Language :: Python
Classifier: Programming Language :: Python :: 3
Classifier: Programming Language :: Python :: 3 :: Only
Classifier: Programming Language :: Python :: 3.8
Classifier: Programming Language :: Python :: 3.9
Classifier: Programming Language :: Python :: 3.10
Classifier: Programming Language :: Python :: 3.11
Classifier: Programming Language :: Python :: 3.12
Classifier: Topic :: Utilities
Classifier: Intended Audience :: End Users/Desktop
Requires-Python: >=3.8
License-File: LICENSE
Requires-Dist: google-api-python-client ~=2.111.0
Requires-Dist: google-auth-httplib2 ~=0.2.0
Requires-Dist: google-auth-oauthlib ~=1.2.0
Requires-Dist: platformdirs ~=4.1.0
Requires-Dist: importlib-resources >=5
Requires-Dist: importlib-metadata >=6
Provides-Extra: dev
Requires-Dist: pip ; extra == 'dev'
Requires-Dist: setuptools ; extra == 'dev'
Requires-Dist: wheel ; extra == 'dev'
Requires-Dist: build ; extra == 'dev'
Requires-Dist: twine ; extra == 'dev'
Requires-Dist: pip-audit ; extra == 'dev'
Requires-Dist: pytest ; extra == 'dev'
Requires-Dist: pytest-mock ; extra == 'dev'
Requires-Dist: pytest-cov ; extra == 'dev'
Requires-Dist: tox ; extra == 'dev'
Requires-Dist: coverage ; extra == 'dev'
Requires-Dist: black ; extra == 'dev'
Requires-Dist: ruff ; extra == 'dev'
Requires-Dist: mypy ; extra == 'dev'
Requires-Dist: pylint ; extra == 'dev'
Requires-Dist: types-dateparser ; extra == 'dev'
Requires-Dist: types-PyYAML ; extra == 'dev'
Requires-Dist: types-requests ; extra == 'dev'
Requires-Dist: types-backports ; extra == 'dev'
Requires-Dist: types-urllib3 ; extra == 'dev'
Requires-Dist: pdoc ; extra == 'dev'
